ralium/__init__.py
ralium/api.py
ralium/builtins.py
ralium/bundle.py
ralium/config.py
ralium/element.py
ralium/navigation.py
ralium/pyhtml.py
ralium/setuptools.py
ralium/window.py
ralium/util/__init__.py
ralium/util/common.py
ralium/util/const.py
ralium/util/exceptions.py
ralium/util/helpers.py
ralium/util/listener.py
ralium/util/log.py
ralium/util/models.py
ralium/web/bridge.py
ralium/web/engine.py
ralium/web/webhook.py
ralium-3.1.8.dist-info/LICENSE
ralium-3.1.8.dist-info/METADATA
ralium-3.1.8.dist-info/WHEEL
ralium-3.1.8.dist-info/top_level.txt
ralium-3.1.8.dist-info/RECORD
