Metadata-Version: 2.1
Name: ralium
Version: 3.1.8
Summary: An easy to use wrapper for pywebview.
Author-email: Isaiah Coroama <coroamaisaiah@gmail.com>
License: GNU GENERAL PUBLIC LICENSE
Project-URL: Homepage, https://github.com/IsaiahCoroama/ralium
Keywords: gui,webkit,ralium,windows,html,web,isaiah,coroama
Classifier: Development Status :: 3 - Alpha
Classifier: Intended Audience :: Developers
Classifier: Programming Language :: Python :: 3.12
Requires-Python: >3.9
License-File: LICENSE
Requires-Dist: beautifulsoup4
Requires-Dist: pyinstaller
Requires-Dist: pywebview
Requires-Dist: pillow
Requires-Dist: lxml
